CHANGES.txt
LICENSE.txt
MANIFEST.in
README.txt
TODO.txt
setup.py
src/p01/__init__.py
src/p01.schema.egg-info/PKG-INFO
src/p01.schema.egg-info/SOURCES.txt
src/p01.schema.egg-info/dependency_links.txt
src/p01.schema.egg-info/namespace_packages.txt
src/p01.schema.egg-info/not-zip-safe
src/p01.schema.egg-info/requires.txt
src/p01.schema.egg-info/top_level.txt
src/p01/schema/README.txt
src/p01/schema/__init__.py
src/p01/schema/checker.txt
src/p01/schema/exceptions.py
src/p01/schema/field.py
src/p01/schema/interfaces.py
src/p01/schema/tests.py